flask_gtts/__init__.py
flask_gtts/about.py
flask_gtts/main.py
flask_gtts/read.html
Flask_gTTS-0.19.dist-info/LICENSE.txt
Flask_gTTS-0.19.dist-info/METADATA
Flask_gTTS-0.19.dist-info/WHEEL
Flask_gTTS-0.19.dist-info/top_level.txt
Flask_gTTS-0.19.dist-info/RECORD
